pelita/__init__.py
pelita/base_utils.py
pelita/exceptions.py
pelita/game.py
pelita/gamestate_filters.py
pelita/layout.py
pelita/maze_generator.py
pelita/network.py
pelita/team.py
pelita/utils.py
pelita/viewer.py
pelita/player/FoodEatingPlayer.py
pelita/player/RandomExplorerPlayer.py
pelita/player/RandomPlayers.py
pelita/player/SmartEatingPlayer.py
pelita/player/SmartRandomPlayer.py
pelita/player/StoppingPlayer.py
pelita/player/__init__.py
pelita/player/base.py
pelita/scripts/__init__.py
pelita/scripts/pelita_main.py
pelita/scripts/pelita_player.py
pelita/scripts/pelita_server.py
pelita/scripts/pelita_tkviewer.py
pelita/scripts/pelita_tournament.py
pelita/scripts/script_utils.py
pelita/tournament/__init__.py
pelita/tournament/knockout_mode.py
pelita/tournament/roundrobin.py
pelita/ui/__init__.py
pelita/ui/tk_canvas.py
pelita/ui/tk_sprites.py
pelita/ui/tk_viewer.py
pelita-2.6.0.dist-info/entry_points.txt
pelita-2.6.0.dist-info/licenses/COPYING
pelita-2.6.0.dist-info/WHEEL
pelita-2.6.0.dist-info/METADATA
pelita-2.6.0.dist-info/RECORD
