Metadata-Version: 2.4
Name: pelita
Version: 2.6.0
Summary: Pelita
Keywords: education
Requires-Python: >= 3.10
Classifier: Development Status :: 5 - Production/Stable
Classifier: Intended Audience :: Education
Classifier: Topic :: Scientific/Engineering :: Artificial Intelligence
Classifier: License :: OSI Approved :: BSD License
Classifier: Programming Language :: Python :: 3.10
Classifier: Programming Language :: Python :: 3.11
Classifier: Programming Language :: Python :: 3.12
Classifier: Programming Language :: Python :: 3.13
License-File: COPYING
Requires-Dist: pyzmq
Requires-Dist: PyYAML
Requires-Dist: numpy
Requires-Dist: networkx
Requires-Dist: pytest>=4
Requires-Dist: zeroconf
Requires-Dist: rich
Requires-Dist: click
Requires-Dist: sphinx ; extra == "doc"
Requires-Dist: pytest>=4 ; extra == "test"
Requires-Dist: pytest-cov ; extra == "test"
Project-URL: Homepage, https://github.com/ASPP/pelita
Provides-Extra: doc
Provides-Extra: test
